<?xml version="1.0" encoding="utf-8" ?>
<dwsync>
<file name="fallback.png" server="172.16.24.3/sys/desaca/" local="130623211882522614" remote="130917885000000000" Dst="1" />
<file name="home5_slide_1.jpg" server="172.16.24.3/sys/desaca/" local="130623211882922620" remote="130917885000000000" Dst="1" />
<file name="home5_slide_2.jpg" server="172.16.24.3/sys/desaca/" local="130623211883172624" remote="130917885000000000" Dst="1" />
<file name="home5_slide_3.jpg" server="172.16.24.3/sys/desaca/" local="130623211883397627" remote="130917885000000000" Dst="1" />
<file name="home5_slide_4.jpg" server="172.16.24.3/sys/desaca/" local="130623211883522629" remote="130917885000000000" Dst="1" />
<file name="home5_slide_5.jpg" server="172.16.24.3/sys/desaca/" local="130623211883697632" remote="130917885000000000" Dst="1" />
<file name="home_page_5_fallback.jpg" server="172.16.24.3/sys/desaca/" local="130623211883897635" remote="130917885000000000" Dst="1" />
<file name="fallback.png" server="itsmacuspana.edu.mx/web/" local="130623211880000000" remote="130933887000000000" Dst="1" />
<file name="home5_slide_1.jpg" server="itsmacuspana.edu.mx/web/" local="130623211880000000" remote="130933887000000000" Dst="1" />
<file name="home5_slide_2.jpg" server="itsmacuspana.edu.mx/web/" local="130623211880000000" remote="130933887000000000" Dst="1" />
<file name="home5_slide_3.jpg" server="itsmacuspana.edu.mx/web/" local="130623211880000000" remote="130933887000000000" Dst="1" />
<file name="home5_slide_4.jpg" server="itsmacuspana.edu.mx/web/" local="130623211880000000" remote="130933887000000000" Dst="1" />
<file name="home5_slide_5.jpg" server="itsmacuspana.edu.mx/web/" local="130623211880000000" remote="130933887000000000" Dst="1" />
<file name="home_page_5_fallback.jpg" server="itsmacuspana.edu.mx/web/" local="130623211880000000" remote="130933887000000000" Dst="1" />
</dwsync>